<?xml version="1.0"?>
<SpineML xsi:schemaLocation="http://www.shef.ac.uk/SpineMLComponentLayer SpineMLComponentLayer.xsd" xmlns="http://www.shef.ac.uk/SpineMLComponentLayer" xmlns:xsi="http://www.w3.org/2001/XMLSchema-instance">
 <ComponentClass type="postsynapse" name="passthroughPS">
  <Annotation>
   <SpineCreator/>
  </Annotation>
  <Dynamics initial_regime="blank">
   <Regime name="blank"/>
   <Alias dimension="?" name="out">
    <MathInline>in</MathInline>
   </Alias>
  </Dynamics>
  <AnalogReducePort dimension="?" name="in" reduce_op="+"/>
  <AnalogSendPort name="out"/>
 </ComponentClass>
</SpineML>
